lunofetch/__init__.py
lunofetch/__main__.py
lunofetch/lunofetch.py
lunofetch-2.0.3.dist-info/licenses/LICENSE
lunofetch-2.0.3.dist-info/METADATA
lunofetch-2.0.3.dist-info/WHEEL
lunofetch-2.0.3.dist-info/entry_points.txt
lunofetch-2.0.3.dist-info/top_level.txt
lunofetch-2.0.3.dist-info/RECORD
