Metadata-Version: 2.4
Name: lunofetch
Version: 2.0.3
Summary: A lightweight Neofetch-like system info tool with custom ASCII logo support.
Author-email: "B. Tharun Bala" <your_email@example.com>
License: MIT
Keywords: system,neofetch,terminal,ascii,linux
Classifier: Programming Language :: Python :: 3
Classifier: License :: OSI Approved :: MIT License
Classifier: Operating System :: POSIX :: Linux
Classifier: Topic :: System :: Monitoring
Requires-Python: >=3.7
License-File: LICENSE
Requires-Dist: psutil
Requires-Dist: distro
Dynamic: license-file
